README.md
setup.cfg
setup.py
yarma/__init__.py
yarma/yarma.py
yarma.egg-info/PKG-INFO
yarma.egg-info/SOURCES.txt
yarma.egg-info/dependency_links.txt
yarma.egg-info/entry_points.txt
yarma.egg-info/requires.txt
yarma.egg-info/top_level.txt